docs/source/conf.py
pyspod/__init__.py
pyspod/emulation/__init__.py
pyspod/emulation/base.py
pyspod/emulation/neural_nets.py
pyspod/pod/__init__.py
pyspod/pod/base.py
pyspod/pod/standard.py
pyspod/pod/utils.py
pyspod/spod/__init__.py
pyspod/spod/base.py
pyspod/spod/standard.py
pyspod/spod/streaming.py
pyspod/spod/utils.py
pyspod/utils/__init__.py
pyspod/utils/errors.py
pyspod/utils/io.py
pyspod/utils/parallel.py
pyspod/utils/postproc.py
pyspod/utils/reader.py
pyspod/utils/weights.py
pyspod/utils/plotting_support/coast.mat
pyspod/utils/plotting_support/coast_centred.mat
tests/test_emulation.py
tests/test_pod_parallel.py
tests/test_pod_serial.py
tests/test_spod_parallel.py
tests/test_spod_serial.py
tests/test_tutorials.py
tests/test_utils_parallel.py
tests/test_utils_serial.py
tutorials/climate/ERA20C_MEI_2D/E20C_MONTHLYMEAN00_1900_2010_MEI.py
tutorials/climate/ERA20C_MEI_2D/ERA20C_MEI_2D.py
tutorials/climate/ERA20C_QBO_3D/E20C_MONTHLYMEAN00_1900_2010_U131128_3D.py
tutorials/climate/ERA20C_QBO_3D/ERA20C_QBO_3D.py
tutorials/tutorial1/tutorial1.py
tutorials/tutorial2/tutorial2.py
pyspod-2.0.0.dist-info/LICENSE.rst
pyspod-2.0.0.dist-info/METADATA
pyspod-2.0.0.dist-info/WHEEL
pyspod-2.0.0.dist-info/top_level.txt
pyspod-2.0.0.dist-info/RECORD
