Metadata-Version: 2.1
Name: pyspod
Version: 2.0.0
Summary: Python Spectral Proper Orthogonal Decomposition
Home-page: https://github.com/MathEXLab/PySPOD
Author: Gianmarco Mengaldo, Marcin Rogoswki, Lisandro Dalcin, Romit Maulik, Andrea Lario
Author-email: mpegim@nus.edu.sg, marcin.rogowski@gmail.com, dalcinl@gmail.com, rmaulik@anl.gov, alario@sissa.it
License: MIT
Keywords: SPOD,spectral proper orthogonal decomposition
Classifier: Intended Audience :: Science/Research
Classifier: License :: OSI Approved :: MIT License
Classifier: Programming Language :: Python :: 3
Classifier: Programming Language :: Python :: 3.7
Classifier: Programming Language :: Python :: 3.8
Classifier: Programming Language :: Python :: 3.9
Classifier: Programming Language :: Python :: 3.10
Classifier: Programming Language :: Python :: 3.11
Classifier: Topic :: Scientific/Engineering :: Mathematics
Requires-Python: >=3.7
License-File: LICENSE.rst
Requires-Dist: psutil
Requires-Dist: tqdm
Requires-Dist: numpy
Requires-Dist: scipy
Requires-Dist: h5py
Requires-Dist: netcdf4
Requires-Dist: xarray
Requires-Dist: matplotlib
Requires-Dist: pyyaml
Requires-Dist: importlib-metadata <5.0 ; python_version < "3.8"
Provides-Extra: ai
Requires-Dist: tensorflow ; extra == 'ai'
Provides-Extra: docs
Requires-Dist: Sphinx ; extra == 'docs'
Requires-Dist: sphinx-rtd-theme ; extra == 'docs'
Provides-Extra: mpi
Requires-Dist: mpi4py ; extra == 'mpi'
Provides-Extra: test
Requires-Dist: pytest ; extra == 'test'
Requires-Dist: pytest-cov ; extra == 'test'
Requires-Dist: pytest-mpi ; extra == 'test'
Requires-Dist: coverage ; extra == 'test'
